{
    "andrewid": "jcortega",
    "1": "1900",
    "2": "Andrew Carnegie's vision was to open a vocational training school for the sons and daughters of working-class Pittsburghers, many of whom worked in his mills",
    "3": "1912",
    "4": "1967",
    "5": "Andrew Mellon and Richard B. Mellon",
    "6": "About Carnegie Mellon",
    "7": "Pittsburgh, Pennsylvania, United States",
    "8": "1967",
    "9": "Carnegie Mellon University College",
    "10": "School of Computer Science",
    "11": "Tepper School of Business",
    "12": "Mel Bochner (A, 1962)",
    "13": "The Tartan",
    "14": "Scotty, the Scottish Terrier",
    "15": "Blue and Gold",
    "16": "Carnegie Mellon's",
    "17": "The Fence, built in 1923, which lies in the middle of the Cut",
    "18": "College of Fine Arts Building",
    "19": "Hunt Library",
    "20": "2016",
    "21": "Randy Pausch's Last Lecture: Really Achieving Your Childhood Dreams",
    "22": "Avie Tevanian",
    "23": "Carnegie Mellon Spring Carnival",
    "24": "The Cut",
    "25": "The concert and marching band of Carnegie Mellon University",
    "26": "Robotics Institute (RI)",
    "27": "Carnegie Mellon",
    "28": "Scott Fahlman",
    "29": "Carnegie Mellon's",
    "30": "Gates-Hillman Center",
    "31": "annual competition at Carnegie Mellon that made its debut in 1994. In this event, robots try (autonomously) to pass through gates, in order, and reach the finish line",
    "32": "Zachary Quinto",
    "33": "Andrew Carnegie",
    "34": "The Fence",
    "35": "A large grassy area",
    "36": "Raj Reddy",
    "37": "Scotch'n'Soda Theatre",
    "38": "Margaret Morrison Carnegie College",
    "39": "Explore CMU",
    "40": "College of Fine Arts",
    "41": "Annual competition at Carnegie Mellon that made its debut in 1994. In this event, robots try (autonomously) to pass through gates, in order, and reach the finish line",
    "42": "Andy Bechtolsheim",
    "43": "Buggy races",
    "44": "The Mall",
    "45": "Computer Interaction Institute",
    "46": "Carnegie Mellon Spring Carnival",
    "47": "The Gates Hillman Complex",
    "48": "Andrew File System",
    "49": "Press Release: CMU Drama Students Explore Theatrical Boundaries in",
    "50": "Deep Thought, predecessor of Deep Blue, co-creator is Feng-hsiung Hsu (Ph.D. 1990) at CMU",
    "51": "Development of the first autonomous car program",
    "52": "Alex Waibel (Speech Recognition)",
    "53": "Time Delay Neural Network",
    "54": "CMU's Boss won the DARPA Grand Challenge (2007)",
    "55": "Robotics Institute",
    "56": "CubeRover",
    "57": "Explore CMU",
    "58": "Held twice a year, in Summer and Winter",
    "59": "20",
    "60": "The Original Pittsburgh Taco Festival",
    "61": "2019",
    "62": "groceries, restaurants, bars, art, tech, and robotics companies",
    "63": "Market Square",
    "64": "Joe Klimchak",
    "65": "Primanti Bros",
    "66": "Syrup Making Workshop",
    "67": "Pittsburgh Restaurant Week",
    "68": "Article Writing Services",
    "69": "The Steel City",
    "70": "Food City",
    "71": "Pittsburgh's Little Italy",
    "72": "Pittsburgh Regional Transit",
    "73": "Carnegie Museum",
    "74": "Food City",
    "75": "Pittsburgh Restaurant Week",
    "76": "Food City",
    "77": "Mrs. T's Pierogies",
    "78": "Pittsburgh",
    "79": "Pittsburgh's Little Italy",
    "80": "Pittsburgh Regional Transit",
    "81": "Parkinson's Ferry",
    "82": "Pittsburgh Sports League Winter Cornhole League",
    "83": "Pittsburgh Restaurant Week",
    "84": "Pittsburgh Regional Transit",
    "85": "Pittsburgh's Little Italy",
    "86": "The Official Lucky's St Patrick's Day Bar",
    "87": "Pittsburgh",
    "88": "Old Residents",
    "89": "The Strip District: Rodman's Great Guns",
    "90": "237 7th Street",
    "91": "Park Rangers",
    "92": "237 7th Street",
    "93": "The Strip District: Rodman's Great Guns",
    "94": "shops, offices, restaurants, and entertainment",
    "95": "Fulton Building",
    "96": "Shadyside",
    "97": "Pittsburgh's Little Italy",
    "98": "Pittsburgh Events",
    "99": "Expanding NCR Credit Card",
    "100": "Driftwood Oven",
    "101": "Soul Food Festival",
    "102": "Pittsburgh Restaurant Week",
    "103": "Pittsburgh Vintage Grand Prix",
    "104": "414 Grant St",
    "105": "Gear Up For The Draft In Pittsburgh",
    "106": "Yinzer",
    "107": "8,016",
    "108": "Public Source's",
    "109": "Southwestern Pennsylvania",
    "110": "Steel City",
    "111": "Shawnee, Seneca, Lenape",
    "112": "Battle of the Monongahela",
    "113": "March 18, 1816",
    "114": "1758 was the year when Shannopin's Town was deserted, and Fort Pitt construction started",
    "115": "Allegheny and Monongahela",
    "116": "Whiskey Rebellion",
    "117": "Rugged topography and dispersed natural resources of coal and gas",
    "118": "Boosted the city's economy with increased production of iron and armaments",
    "119": "April 10, 1845",
    "120": "Fort Pitt Blockhouse",
    "121": "H.J. Heinz Company",
    "122": "U.S. Steel formation",
    "123": "Diversified to light industries",
    "124": "Renaissance II (1977)",
    "125": "University of Pittsburgh",
    "126": "Sports History",
    "127": "446",
    "128": "Point State Park",
    "129": "Squirrel Hill",
    "130": "Cathedral of Learning",
    "131": "Alcoa",
    "132": "Homestead Strike",
    "133": "North Shore",
    "134": "Smoketown' Traces The Rise And Fall Of",
    "135": "Carnegie Museum of Art",
    "136": "1979 (Pirates World Series championship, Steelers Super Bowl XIV)",
    "137": "Mexican War Streets",
    "138": "Phipps Conservatory and Botanical Gardens",
    "139": "Acrisure Stadium",
    "140": "Carnegie Science Center",
    "141": "Scottish-American industrialist and philanthropist",
    "142": "Shadyside",
    "143": "Highlighting Pittsburgh's",
    "144": "Pittsburgh Cancer Institute",
    "145": "Street Bridge",
    "146": "650 Smithfield Street",
    "147": "Primanti Brothers sandwiches, Chipped chopped ham sandwiches, Kielbasa sandwiches",
    "148": "Allegheny County Sheriff",
    "149": "302,971",
    "150": "High technology, finance, education, and services",
    "151": "Carnegie Mellon University",
    "152": "The Golden Triangle",
    "153": "Duquesne University Red Masquers",
    "154": "Oakland",
    "155": "Home to 4,000 animals, including many endangered species",
    "156": "Roberto Clemente Bridge",
    "157": "The Strip District is famous for its open-air marketplace by day and a clubbing destination by night"
}